[1,["21e0f019-14b1-4a12-90c8-e38ec853ebf0@6c48a"],["_textureSource"],["cc.SpriteFrame"],0,[{"name":"10113","rect":{"x":1,"y":0,"width":215,"height":280},"offset":{"x":0.5,"y":1.5},"originalSize":{"width":216,"height":283},"rotated":false,"capInsets":[0,0,0,0],"vertices":{"rawPosition":[-107.5,-140,0,107.5,-140,0,-107.5,140,0,107.5,140,0],"indexes":[0,1,2,2,1,3],"uv":[1,283,216,283,1,3,216,3],"nuv":[0.004629629629629629,0.01060070671378092,1,0.01060070671378092,0.004629629629629629,1,1,1],"minPos":{"x":-107.5,"y":-140,"z":0},"maxPos":{"x":107.5,"y":140,"z":0}},"packable":true,"pixelsToUnit":100,"pivot":{"x":0.5,"y":0.5},"meshType":0}],[0],0,[0],[0],[0]]
